{
  "db_name": "PostgreSQL",
  "query": "SELECT votee_id, create_date FROM vote WHERE guild_id = $1 AND voter_id = $2 ORDER BY create_date DESC LIMIT 1",
  "describe": {
    "columns": [
      {
        "ordinal": 0,
        "name": "votee_id",
        "type_info": "Int8"
      },
      {
        "ordinal": 1,
        "name": "create_date",
        "type_info": "Timestamptz"
      }
    ],
    "parameters": {
      "Left": [
        "Int8",
        "Int8"
      ]
    },
    "nullable": [
      false,
      false
    ]
  },
  "hash": "6f5cbe88bbba1f2544d7acdc79ecbfac1e2a40abfebed14c8d035f91b0dea082"
}
